[
  {
    "trend_arrow": "FLAT", 
    "display_time": "2017-04-26T01:54:33-07:00", 
    "noise": 1, 
    "system_time": "2017-04-26T08:37:51-07:00", 
    "direction": "Flat", 
    "sgv": 102, 
    "dateString": "2017-04-26T01:54:33-07:00", 
    "date": 1493196873000, 
    "unfiltered": 108688, 
    "filtered": 106288, 
    "device": "openaps://indy-e1/cgm", 
    "rssi": 443, 
    "type": "sgv", 
    "glucose": 102
  }, 
  {
    "trend_arrow": "FLAT", 
    "display_time": "2017-04-26T01:49:33-07:00", 
    "noise": 1, 
    "system_time": "2017-04-26T08:32:51-07:00", 
    "direction": "Flat", 
    "sgv": 100, 
    "dateString": "2017-04-26T01:49:33-07:00", 
    "date": 1493196573000, 
    "unfiltered": 107312, 
    "filtered": 105520, 
    "device": "openaps://indy-e1/cgm", 
    "rssi": 444, 
    "type": "sgv", 
    "glucose": 100
  }
]