[
  {
    "trend_arrow": "45_UP", 
    "display_time": "2017-04-27T11:29:27-07:00", 
    "noise": 1, 
    "system_time": "2017-04-27T18:12:45-07:00", 
    "direction": "FortyFiveUp", 
    "sgv": 157, 
    "dateString": "2017-04-27T11:29:27-07:00", 
    "date": 1493317767000, 
    "unfiltered": 149824, 
    "filtered": 143328, 
    "device": "openaps://indy-e1/cgm", 
    "rssi": 446, 
    "type": "sgv", 
    "glucose": 157
  }, 
  {
    "trend_arrow": "45_UP", 
    "display_time": "2017-04-27T11:24:27-07:00", 
    "noise": 1, 
    "system_time": "2017-04-27T18:07:44-07:00", 
    "direction": "FortyFiveUp", 
    "sgv": 153, 
    "dateString": "2017-04-27T11:24:27-07:00", 
    "date": 1493317467000, 
    "unfiltered": 147264, 
    "filtered": 137632, 
    "device": "openaps://indy-e1/cgm", 
    "rssi": 191, 
    "type": "sgv", 
    "glucose": 153
  }
]