[
  {
    "trend_arrow": "45_DOWN", 
    "display_time": "2017-04-15T15:59:25-07:00", 
    "noise": 1, 
    "system_time": "2017-04-15T22:42:59-07:00", 
    "direction": "FortyFiveDown", 
    "sgv": 140, 
    "dateString": "2017-04-15T15:59:25-07:00", 
    "date": 1492297165000, 
    "unfiltered": 144608, 
    "filtered": 156864, 
    "device": "openaps://indy-e1/cgm", 
    "rssi": 198, 
    "type": "sgv", 
    "glucose": 140
  }, 
  {
    "trend_arrow": "FLAT", 
    "display_time": "2017-04-15T15:54:25-07:00", 
    "noise": 1, 
    "system_time": "2017-04-15T22:37:59-07:00", 
    "direction": "Flat", 
    "sgv": 151, 
    "dateString": "2017-04-15T15:54:25-07:00", 
    "date": 1492296865000, 
    "unfiltered": 154720, 
    "filtered": 158656, 
    "device": "openaps://indy-e1/cgm", 
    "rssi": 183, 
    "type": "sgv", 
    "glucose": 151
  }
]