[
  {
    "trend_arrow": "FLAT", 
    "display_time": "2017-04-11T08:10:16-07:00", 
    "noise": 1, 
    "system_time": "2017-04-11T15:09:15-07:00", 
    "direction": "Flat", 
    "sgv": 131, 
    "dateString": "2017-04-11T08:10:16-07:00", 
    "date": 1491923416000, 
    "unfiltered": 148608, 
    "filtered": 153728, 
    "device": "openaps://indy-e1/cgm", 
    "rssi": 429, 
    "type": "sgv", 
    "glucose": 131
  }, 
  {
    "trend_arrow": "FLAT", 
    "display_time": "2017-04-11T08:05:15-07:00", 
    "noise": 1, 
    "system_time": "2017-04-11T15:04:15-07:00", 
    "direction": "Flat", 
    "sgv": 135, 
    "dateString": "2017-04-11T08:05:15-07:00", 
    "date": 1491923115000, 
    "unfiltered": 153024, 
    "filtered": 154688, 
    "device": "openaps://indy-e1/cgm", 
    "rssi": 187, 
    "type": "sgv", 
    "glucose": 135
  }
]