[
  {
    "trend_arrow": "FLAT", 
    "display_time": "2017-03-29T10:15:54-07:00", 
    "noise": 1, 
    "system_time": "2017-03-29T17:14:53-07:00", 
    "direction": "Flat", 
    "sgv": 147, 
    "dateString": "2017-03-29T10:15:54-07:00", 
    "date": 1490807754000, 
    "unfiltered": 164704, 
    "filtered": 164128, 
    "device": "openaps://indy-e1/cgm", 
    "rssi": 206, 
    "type": "sgv", 
    "glucose": 147
  }, 
  {
    "trend_arrow": "FLAT", 
    "display_time": "2017-03-29T10:10:54-07:00", 
    "noise": 1, 
    "system_time": "2017-03-29T17:09:53-07:00", 
    "direction": "Flat", 
    "sgv": 147, 
    "dateString": "2017-03-29T10:10:54-07:00", 
    "date": 1490807454000, 
    "unfiltered": 164288, 
    "filtered": 164800, 
    "device": "openaps://indy-e1/cgm", 
    "rssi": 196, 
    "type": "sgv", 
    "glucose": 147
  }
]