[
  {
    "trend_arrow": "FLAT", 
    "display_time": "2017-03-25T13:00:22-07:00", 
    "noise": 1, 
    "system_time": "2017-03-25T19:44:24-07:00", 
    "direction": "Flat", 
    "sgv": 106, 
    "dateString": "2017-03-25T13:00:22-07:00", 
    "date": 1490472022000, 
    "unfiltered": 111664, 
    "filtered": 108032, 
    "device": "openaps://indy-e1/cgm", 
    "rssi": 195, 
    "type": "sgv", 
    "glucose": 106
  }, 
  {
    "trend_arrow": "FLAT", 
    "display_time": "2017-03-25T12:55:22-07:00", 
    "noise": 1, 
    "system_time": "2017-03-25T19:39:24-07:00", 
    "direction": "Flat", 
    "sgv": 104, 
    "dateString": "2017-03-25T12:55:22-07:00", 
    "date": 1490471722000, 
    "unfiltered": 110160, 
    "filtered": 106560, 
    "device": "openaps://indy-e1/cgm", 
    "rssi": 194, 
    "type": "sgv", 
    "glucose": 104
  }
]