[
  {
    "trend_arrow": "45_UP", 
    "display_time": "2017-04-28T07:49:23-07:00", 
    "noise": 1, 
    "system_time": "2017-04-28T14:32:41-07:00", 
    "direction": "FortyFiveUp", 
    "sgv": 135, 
    "dateString": "2017-04-28T07:49:23-07:00", 
    "date": 1493390963000, 
    "unfiltered": 133280, 
    "filtered": 122304, 
    "device": "openaps://indy-e1/cgm", 
    "rssi": 182, 
    "type": "sgv", 
    "glucose": 135
  }, 
  {
    "trend_arrow": "45_UP", 
    "display_time": "2017-04-28T07:44:23-07:00", 
    "noise": 1, 
    "system_time": "2017-04-28T14:27:41-07:00", 
    "direction": "FortyFiveUp", 
    "sgv": 125, 
    "dateString": "2017-04-28T07:44:23-07:00", 
    "date": 1493390663000, 
    "unfiltered": 126624, 
    "filtered": 116240, 
    "device": "openaps://indy-e1/cgm", 
    "rssi": 183, 
    "type": "sgv", 
    "glucose": 125
  }
]