[
  {
    "trend_arrow": "45_UP", 
    "display_time": "2017-04-07T18:00:26-07:00", 
    "noise": 1, 
    "system_time": "2017-04-08T00:59:25-07:00", 
    "direction": "FortyFiveUp", 
    "sgv": 148, 
    "dateString": "2017-04-07T18:00:26-07:00", 
    "date": 1491613226000, 
    "unfiltered": 168672, 
    "filtered": 164608, 
    "device": "openaps://indy-e1/cgm", 
    "rssi": 191, 
    "type": "sgv", 
    "glucose": 148
  }, 
  {
    "trend_arrow": "45_UP", 
    "display_time": "2017-04-07T17:55:26-07:00", 
    "noise": 1, 
    "system_time": "2017-04-08T00:54:25-07:00", 
    "direction": "FortyFiveUp", 
    "sgv": 145, 
    "dateString": "2017-04-07T17:55:26-07:00", 
    "date": 1491612926000, 
    "unfiltered": 165152, 
    "filtered": 158592, 
    "device": "openaps://indy-e1/cgm", 
    "rssi": 192, 
    "type": "sgv", 
    "glucose": 145
  }
]