[
  {
    "trend_arrow": "FLAT", 
    "display_time": "2017-04-03T11:55:39-07:00", 
    "noise": 1, 
    "system_time": "2017-04-03T18:54:38-07:00", 
    "direction": "Flat", 
    "sgv": 120, 
    "dateString": "2017-04-03T11:55:39-07:00", 
    "date": 1491245739000, 
    "unfiltered": 135168, 
    "filtered": 139456, 
    "device": "openaps://indy-e1/cgm", 
    "rssi": 201, 
    "type": "sgv", 
    "glucose": 120
  }, 
  {
    "trend_arrow": "FLAT", 
    "display_time": "2017-04-03T11:50:39-07:00", 
    "noise": 1, 
    "system_time": "2017-04-03T18:49:38-07:00", 
    "direction": "Flat", 
    "sgv": 124, 
    "dateString": "2017-04-03T11:50:39-07:00", 
    "date": 1491245439000, 
    "unfiltered": 138240, 
    "filtered": 142432, 
    "device": "openaps://indy-e1/cgm", 
    "rssi": 204, 
    "type": "sgv", 
    "glucose": 124
  }
]