[
  {
    "trend_arrow": "FLAT", 
    "display_time": "2017-04-02T09:25:42-07:00", 
    "noise": 1, 
    "system_time": "2017-04-02T16:24:41-07:00", 
    "direction": "Flat", 
    "sgv": 101, 
    "dateString": "2017-04-02T09:25:42-07:00", 
    "date": 1491150342000, 
    "unfiltered": 105328, 
    "filtered": 106800, 
    "device": "openaps://indy-e1/cgm", 
    "rssi": 190, 
    "type": "sgv", 
    "glucose": 101
  }, 
  {
    "trend_arrow": "FLAT", 
    "display_time": "2017-04-02T09:20:43-07:00", 
    "noise": 1, 
    "system_time": "2017-04-02T16:19:42-07:00", 
    "direction": "Flat", 
    "sgv": 102, 
    "dateString": "2017-04-02T09:20:43-07:00", 
    "date": 1491150043000, 
    "unfiltered": 106176, 
    "filtered": 108528, 
    "device": "openaps://indy-e1/cgm", 
    "rssi": 434, 
    "type": "sgv", 
    "glucose": 102
  }
]