[
  {
    "trend_arrow": "FLAT", 
    "display_time": "2017-04-08T06:45:24-07:00", 
    "noise": 1, 
    "system_time": "2017-04-08T13:44:24-07:00", 
    "direction": "Flat", 
    "sgv": 94, 
    "dateString": "2017-04-08T06:45:24-07:00", 
    "date": 1491659124000, 
    "unfiltered": 114384, 
    "filtered": 120640, 
    "device": "openaps://indy-e1/cgm", 
    "rssi": 204, 
    "type": "sgv", 
    "glucose": 94
  }, 
  {
    "trend_arrow": "45_DOWN", 
    "display_time": "2017-04-08T06:40:24-07:00", 
    "noise": 1, 
    "system_time": "2017-04-08T13:39:24-07:00", 
    "direction": "FortyFiveDown", 
    "sgv": 98, 
    "dateString": "2017-04-08T06:40:24-07:00", 
    "date": 1491658824000, 
    "unfiltered": 118448, 
    "filtered": 125920, 
    "device": "openaps://indy-e1/cgm", 
    "rssi": 199, 
    "type": "sgv", 
    "glucose": 98
  }
]