[
  {
    "trend_arrow": "FLAT", 
    "display_time": "2017-04-04T12:05:36-07:00", 
    "noise": 1, 
    "system_time": "2017-04-04T19:04:35-07:00", 
    "direction": "Flat", 
    "sgv": 130, 
    "dateString": "2017-04-04T12:05:36-07:00", 
    "date": 1491332736000, 
    "unfiltered": 133312, 
    "filtered": 139584, 
    "device": "openaps://indy-e1/cgm", 
    "rssi": 201, 
    "type": "sgv", 
    "glucose": 130
  }, 
  {
    "trend_arrow": "FLAT", 
    "display_time": "2017-04-04T12:00:36-07:00", 
    "noise": 1, 
    "system_time": "2017-04-04T18:59:35-07:00", 
    "direction": "Flat", 
    "sgv": 137, 
    "dateString": "2017-04-04T12:00:36-07:00", 
    "date": 1491332436000, 
    "unfiltered": 138400, 
    "filtered": 143328, 
    "device": "openaps://indy-e1/cgm", 
    "rssi": 191, 
    "type": "sgv", 
    "glucose": 137
  }
]