[
  {
    "trend_arrow": "FLAT", 
    "display_time": "2017-04-17T02:09:19-07:00", 
    "noise": 1, 
    "system_time": "2017-04-17T08:52:54-07:00", 
    "direction": "Flat", 
    "sgv": 106, 
    "dateString": "2017-04-17T02:09:19-07:00", 
    "date": 1492420159000, 
    "unfiltered": 107936, 
    "filtered": 105280, 
    "device": "openaps://indy-e1/cgm", 
    "rssi": 186, 
    "type": "sgv", 
    "glucose": 106
  }, 
  {
    "trend_arrow": "FLAT", 
    "display_time": "2017-04-17T02:04:19-07:00", 
    "noise": 1, 
    "system_time": "2017-04-17T08:47:54-07:00", 
    "direction": "Flat", 
    "sgv": 104, 
    "dateString": "2017-04-17T02:04:19-07:00", 
    "date": 1492419859000, 
    "unfiltered": 106128, 
    "filtered": 103712, 
    "device": "openaps://indy-e1/cgm", 
    "rssi": 185, 
    "type": "sgv", 
    "glucose": 104
  }
]