[
  {
    "trend_arrow": "45_DOWN", 
    "display_time": "2017-04-03T16:50:38-07:00", 
    "noise": 1, 
    "system_time": "2017-04-03T23:49:37-07:00", 
    "direction": "FortyFiveDown", 
    "sgv": 58, 
    "dateString": "2017-04-03T16:50:38-07:00", 
    "date": 1491263438000, 
    "unfiltered": 83200, 
    "filtered": 91792, 
    "device": "openaps://indy-e1/cgm", 
    "rssi": 197, 
    "type": "sgv", 
    "glucose": 58
  }, 
  {
    "trend_arrow": "45_DOWN", 
    "display_time": "2017-04-03T16:45:38-07:00", 
    "noise": 1, 
    "system_time": "2017-04-03T23:44:38-07:00", 
    "direction": "FortyFiveDown", 
    "sgv": 63, 
    "dateString": "2017-04-03T16:45:38-07:00", 
    "date": 1491263138000, 
    "unfiltered": 87280, 
    "filtered": 100192, 
    "device": "openaps://indy-e1/cgm", 
    "rssi": 213, 
    "type": "sgv", 
    "glucose": 63
  }
]