[
  {
    "trend_arrow": "45_UP", 
    "display_time": "2017-03-25T20:55:21-07:00", 
    "noise": 1, 
    "system_time": "2017-03-26T03:39:23-07:00", 
    "direction": "FortyFiveUp", 
    "sgv": 243, 
    "dateString": "2017-03-25T20:55:21-07:00", 
    "date": 1490500521000, 
    "unfiltered": 198496, 
    "filtered": 193568, 
    "device": "openaps://indy-e1/cgm", 
    "rssi": 212, 
    "type": "sgv", 
    "glucose": 243
  }, 
  {
    "trend_arrow": "45_UP", 
    "display_time": "2017-03-25T20:50:21-07:00", 
    "noise": 1, 
    "system_time": "2017-03-26T03:34:23-07:00", 
    "direction": "FortyFiveUp", 
    "sgv": 236, 
    "dateString": "2017-03-25T20:50:21-07:00", 
    "date": 1490500221000, 
    "unfiltered": 194080, 
    "filtered": 187584, 
    "device": "openaps://indy-e1/cgm", 
    "rssi": 209, 
    "type": "sgv", 
    "glucose": 236
  }
]