[
  {
    "trend_arrow": "FLAT", 
    "display_time": "2017-04-09T15:55:20-07:00", 
    "noise": 1, 
    "system_time": "2017-04-09T22:54:20-07:00", 
    "direction": "Flat", 
    "sgv": 90, 
    "dateString": "2017-04-09T15:55:20-07:00", 
    "date": 1491778520000, 
    "unfiltered": 117616, 
    "filtered": 113488, 
    "device": "openaps://indy-e1/cgm", 
    "rssi": 198, 
    "type": "sgv", 
    "glucose": 90
  }, 
  {
    "trend_arrow": "FLAT", 
    "display_time": "2017-04-09T15:50:20-07:00", 
    "noise": 1, 
    "system_time": "2017-04-09T22:49:20-07:00", 
    "direction": "Flat", 
    "sgv": 84, 
    "dateString": "2017-04-09T15:50:20-07:00", 
    "date": 1491778220000, 
    "unfiltered": 111728, 
    "filtered": 113936, 
    "device": "openaps://indy-e1/cgm", 
    "rssi": 189, 
    "type": "sgv", 
    "glucose": 84
  }
]