[
  {
    "trend_arrow": "DOUBLE_DOWN", 
    "display_time": "2017-04-23T17:09:09-07:00", 
    "noise": 1, 
    "system_time": "2017-04-24T00:08:05-07:00", 
    "direction": "DoubleDown", 
    "sgv": 86, 
    "dateString": "2017-04-23T17:09:09-07:00", 
    "date": 1492992549000, 
    "unfiltered": 108080, 
    "filtered": 134272, 
    "device": "openaps://indy-e1/cgm", 
    "rssi": 205, 
    "type": "sgv", 
    "glucose": 86
  }, 
  {
    "trend_arrow": "DOUBLE_DOWN", 
    "display_time": "2017-04-23T17:04:09-07:00", 
    "noise": 1, 
    "system_time": "2017-04-24T00:03:05-07:00", 
    "direction": "DoubleDown", 
    "sgv": 109, 
    "dateString": "2017-04-23T17:04:09-07:00", 
    "date": 1492992249000, 
    "unfiltered": 127072, 
    "filtered": 147904, 
    "device": "openaps://indy-e1/cgm", 
    "rssi": 216, 
    "type": "sgv", 
    "glucose": 109
  }
]