[
  {
    "trend_arrow": "FLAT", 
    "display_time": "2017-04-08T15:10:23-07:00", 
    "noise": 1, 
    "system_time": "2017-04-08T22:09:23-07:00", 
    "direction": "Flat", 
    "sgv": 168, 
    "dateString": "2017-04-08T15:10:23-07:00", 
    "date": 1491689423000, 
    "unfiltered": 188832, 
    "filtered": 192768, 
    "device": "openaps://indy-e1/cgm", 
    "rssi": 205, 
    "type": "sgv", 
    "glucose": 168
  }, 
  {
    "trend_arrow": "FLAT", 
    "display_time": "2017-04-08T15:05:23-07:00", 
    "noise": 1, 
    "system_time": "2017-04-08T22:04:23-07:00", 
    "direction": "Flat", 
    "sgv": 170, 
    "dateString": "2017-04-08T15:05:23-07:00", 
    "date": 1491689123000, 
    "unfiltered": 189856, 
    "filtered": 194624, 
    "device": "openaps://indy-e1/cgm", 
    "rssi": 197, 
    "type": "sgv", 
    "glucose": 170
  }
]