[
  {
    "trend_arrow": "45_DOWN", 
    "display_time": "2017-04-26T10:04:31-07:00", 
    "noise": 1, 
    "system_time": "2017-04-26T16:47:49-07:00", 
    "direction": "FortyFiveDown", 
    "sgv": 97, 
    "dateString": "2017-04-26T10:04:31-07:00", 
    "date": 1493226271000, 
    "unfiltered": 108720, 
    "filtered": 113296, 
    "device": "openaps://indy-e1/cgm", 
    "rssi": 208, 
    "type": "sgv", 
    "glucose": 97
  }, 
  {
    "trend_arrow": "45_DOWN", 
    "display_time": "2017-04-26T09:59:31-07:00", 
    "noise": 1, 
    "system_time": "2017-04-26T16:42:49-07:00", 
    "direction": "FortyFiveDown", 
    "sgv": 100, 
    "dateString": "2017-04-26T09:59:31-07:00", 
    "date": 1493225971000, 
    "unfiltered": 111104, 
    "filtered": 117648, 
    "device": "openaps://indy-e1/cgm", 
    "rssi": 195, 
    "type": "sgv", 
    "glucose": 100
  }
]