[
  {
    "trend_arrow": "45_DOWN", 
    "display_time": "2017-03-28T14:15:10-07:00", 
    "noise": 1, 
    "system_time": "2017-03-28T20:59:12-07:00", 
    "direction": "FortyFiveDown", 
    "sgv": 88, 
    "dateString": "2017-03-28T14:15:10-07:00", 
    "date": 1490735710000, 
    "unfiltered": 101136, 
    "filtered": 107136, 
    "device": "openaps://indy-e1/cgm", 
    "rssi": 182, 
    "type": "sgv", 
    "glucose": 88
  }, 
  {
    "trend_arrow": "45_DOWN", 
    "display_time": "2017-03-28T14:10:11-07:00", 
    "noise": 1, 
    "system_time": "2017-03-28T20:54:12-07:00", 
    "direction": "FortyFiveDown", 
    "sgv": 93, 
    "dateString": "2017-03-28T14:10:11-07:00", 
    "date": 1490735411000, 
    "unfiltered": 104912, 
    "filtered": 113392, 
    "device": "openaps://indy-e1/cgm", 
    "rssi": 186, 
    "type": "sgv", 
    "glucose": 93
  }
]