[
  {
    "trend_arrow": "FLAT", 
    "display_time": "2017-04-08T17:35:23-07:00", 
    "noise": 1, 
    "system_time": "2017-04-09T00:34:22-07:00", 
    "direction": "Flat", 
    "sgv": 114, 
    "dateString": "2017-04-08T17:35:23-07:00", 
    "date": 1491698123000, 
    "unfiltered": 134368, 
    "filtered": 133248, 
    "device": "openaps://indy-e1/cgm", 
    "rssi": 205, 
    "type": "sgv", 
    "glucose": 114
  }, 
  {
    "trend_arrow": "FLAT", 
    "display_time": "2017-04-08T17:30:23-07:00", 
    "noise": 1, 
    "system_time": "2017-04-09T00:29:23-07:00", 
    "direction": "Flat", 
    "sgv": 114, 
    "dateString": "2017-04-08T17:30:23-07:00", 
    "date": 1491697823000, 
    "unfiltered": 134432, 
    "filtered": 130576, 
    "device": "openaps://indy-e1/cgm", 
    "rssi": 190, 
    "type": "sgv", 
    "glucose": 114
  }
]