[
  {
    "trend_arrow": "FLAT", 
    "display_time": "2017-04-14T19:04:28-07:00", 
    "noise": 1, 
    "system_time": "2017-04-15T01:48:03-07:00", 
    "direction": "Flat", 
    "sgv": 73, 
    "dateString": "2017-04-14T19:04:28-07:00", 
    "date": 1492221868000, 
    "unfiltered": 77168, 
    "filtered": 80368, 
    "device": "openaps://indy-e1/cgm", 
    "rssi": 184, 
    "type": "sgv", 
    "glucose": 73
  }, 
  {
    "trend_arrow": "45_DOWN", 
    "display_time": "2017-04-14T18:59:28-07:00", 
    "noise": 1, 
    "system_time": "2017-04-15T01:43:03-07:00", 
    "direction": "FortyFiveDown", 
    "sgv": 75, 
    "dateString": "2017-04-14T18:59:28-07:00", 
    "date": 1492221568000, 
    "unfiltered": 78624, 
    "filtered": 84624, 
    "device": "openaps://indy-e1/cgm", 
    "rssi": 184, 
    "type": "sgv", 
    "glucose": 75
  }
]