[
  {
    "trend_arrow": "45_UP", 
    "display_time": "2017-04-19T16:09:20-07:00", 
    "noise": 1, 
    "system_time": "2017-04-19T23:08:16-07:00", 
    "direction": "FortyFiveUp", 
    "sgv": 118, 
    "dateString": "2017-04-19T16:09:20-07:00", 
    "date": 1492643360000, 
    "unfiltered": 125872, 
    "filtered": 116720, 
    "device": "openaps://indy-e1/cgm", 
    "rssi": 195, 
    "type": "sgv", 
    "glucose": 118
  }, 
  {
    "trend_arrow": "45_UP", 
    "display_time": "2017-04-19T16:04:20-07:00", 
    "noise": 1, 
    "system_time": "2017-04-19T23:03:16-07:00", 
    "direction": "FortyFiveUp", 
    "sgv": 110, 
    "dateString": "2017-04-19T16:04:20-07:00", 
    "date": 1492643060000, 
    "unfiltered": 119408, 
    "filtered": 111856, 
    "device": "openaps://indy-e1/cgm", 
    "rssi": 199, 
    "type": "sgv", 
    "glucose": 110
  }
]