[
  {
    "trend_arrow": "DOUBLE_UP", 
    "display_time": "2017-03-31T18:10:47-07:00", 
    "noise": 1, 
    "system_time": "2017-04-01T01:09:46-07:00", 
    "direction": "DoubleUp", 
    "sgv": 137, 
    "dateString": "2017-03-31T18:10:47-07:00", 
    "date": 1491009047000, 
    "unfiltered": 138208, 
    "filtered": 117696, 
    "device": "openaps://indy-e1/cgm", 
    "rssi": 194, 
    "type": "sgv", 
    "glucose": 137
  }, 
  {
    "trend_arrow": "DOUBLE_UP", 
    "display_time": "2017-03-31T18:05:47-07:00", 
    "noise": 1, 
    "system_time": "2017-04-01T01:04:46-07:00", 
    "direction": "DoubleUp", 
    "sgv": 125, 
    "dateString": "2017-03-31T18:05:47-07:00", 
    "date": 1491008747000, 
    "unfiltered": 128560, 
    "filtered": 103744, 
    "device": "openaps://indy-e1/cgm", 
    "rssi": 183, 
    "type": "sgv", 
    "glucose": 125
  }
]