[
  {
    "trend_arrow": "FLAT", 
    "display_time": "2017-03-26T12:05:19-07:00", 
    "noise": 1, 
    "system_time": "2017-03-26T18:49:20-07:00", 
    "direction": "Flat", 
    "sgv": 181, 
    "dateString": "2017-03-26T12:05:19-07:00", 
    "device": "openaps://indy-e1/cgm", 
    "unfiltered": 159520, 
    "rssi": 202, 
    "date": 1490555119000, 
    "filtered": 157856, 
    "type": "sgv", 
    "glucose": 181
  }, 
  {
    "trend_arrow": "FLAT", 
    "display_time": "2017-03-26T12:00:19-07:00", 
    "noise": 1, 
    "system_time": "2017-03-26T18:44:20-07:00", 
    "direction": "Flat", 
    "sgv": 176, 
    "dateString": "2017-03-26T12:00:19-07:00", 
    "device": "openaps://indy-e1/cgm", 
    "unfiltered": 156192, 
    "rssi": 193, 
    "date": 1490554819000, 
    "filtered": 158624, 
    "type": "sgv", 
    "glucose": 176
  }
]