[
  {
    "trend_arrow": "FLAT", 
    "display_time": "2017-04-07T09:55:27-07:00", 
    "noise": 1, 
    "system_time": "2017-04-07T16:54:26-07:00", 
    "direction": "Flat", 
    "sgv": 98, 
    "dateString": "2017-04-07T09:55:27-07:00", 
    "device": "openaps://indy-e1/cgm", 
    "unfiltered": 117904, 
    "rssi": 188, 
    "date": 1491584127000, 
    "filtered": 124224, 
    "type": "sgv", 
    "glucose": 98
  }, 
  {
    "trend_arrow": "FLAT", 
    "display_time": "2017-04-07T09:50:27-07:00", 
    "noise": 1, 
    "system_time": "2017-04-07T16:49:26-07:00", 
    "direction": "Flat", 
    "sgv": 103, 
    "dateString": "2017-04-07T09:50:27-07:00", 
    "device": "openaps://indy-e1/cgm", 
    "unfiltered": 123072, 
    "rssi": 193, 
    "date": 1491583827000, 
    "filtered": 126400, 
    "type": "sgv", 
    "glucose": 103
  }
]