[
  {
    "trend_arrow": "DOUBLE_DOWN", 
    "display_time": "2017-04-04T16:45:35-07:00", 
    "noise": 1, 
    "system_time": "2017-04-04T23:44:35-07:00", 
    "direction": "DoubleDown", 
    "sgv": 57, 
    "dateString": "2017-04-04T16:45:35-07:00", 
    "device": "openaps://indy-e1/cgm", 
    "unfiltered": 75392, 
    "rssi": 196, 
    "date": 1491349535000, 
    "filtered": 99152, 
    "type": "sgv", 
    "glucose": 57
  }, 
  {
    "trend_arrow": "DOUBLE_DOWN", 
    "display_time": "2017-04-04T16:40:35-07:00", 
    "noise": 1, 
    "system_time": "2017-04-04T23:39:35-07:00", 
    "direction": "DoubleDown", 
    "sgv": 74, 
    "dateString": "2017-04-04T16:40:35-07:00", 
    "device": "openaps://indy-e1/cgm", 
    "unfiltered": 88688, 
    "rssi": 198, 
    "date": 1491349235000, 
    "filtered": 116176, 
    "type": "sgv", 
    "glucose": 74
  }
]