[
  {
    "trend_arrow": "FLAT", 
    "display_time": "2017-03-30T00:55:52-07:00", 
    "noise": 1, 
    "system_time": "2017-03-30T07:54:52-07:00", 
    "direction": "Flat", 
    "sgv": 117, 
    "dateString": "2017-03-30T00:55:52-07:00", 
    "device": "openaps://indy-e1/cgm", 
    "unfiltered": 152736, 
    "rssi": 189, 
    "date": 1490860552000, 
    "filtered": 144544, 
    "type": "sgv", 
    "glucose": 117
  }, 
  {
    "trend_arrow": "FLAT", 
    "display_time": "2017-03-30T00:50:52-07:00", 
    "noise": 1, 
    "system_time": "2017-03-30T07:49:52-07:00", 
    "direction": "Flat", 
    "sgv": 111, 
    "dateString": "2017-03-30T00:50:52-07:00", 
    "device": "openaps://indy-e1/cgm", 
    "unfiltered": 145856, 
    "rssi": 188, 
    "date": 1490860252000, 
    "filtered": 141568, 
    "type": "sgv", 
    "glucose": 111
  }
]