[
  {
    "trend_arrow": "45_UP", 
    "system_time": "2017-04-24T17:27:57", 
    "noise": 1, 
    "direction": "FortyFiveUp", 
    "sgv": 117, 
    "display_time": "2017-04-24T10:44:40", 
    "date": 1493055880000.0, 
    "dateString": "2017-04-24T10:44:40", 
    "unfiltered": 121488, 
    "filtered": 110528, 
    "device": "openaps://indy-e1/cgm", 
    "rssi": 195, 
    "type": "sgv", 
    "glucose": 117
  }, 
  {
    "trend_arrow": "45_UP", 
    "system_time": "2017-04-24T17:22:57", 
    "noise": 1, 
    "direction": "FortyFiveUp", 
    "sgv": 109, 
    "display_time": "2017-04-24T10:39:40", 
    "date": 1493055580000.0, 
    "dateString": "2017-04-24T10:39:40", 
    "unfiltered": 115712, 
    "filtered": 105760, 
    "device": "openaps://indy-e1/cgm", 
    "rssi": 182, 
    "type": "sgv", 
    "glucose": 109
  }, 
  {
    "trend_arrow": "FLAT", 
    "system_time": "2017-04-24T17:17:57", 
    "noise": 1, 
    "direction": "Flat", 
    "sgv": 98, 
    "display_time": "2017-04-24T10:34:40", 
    "date": 1493055280000.0, 
    "dateString": "2017-04-24T10:34:40", 
    "unfiltered": 108768, 
    "filtered": 103808, 
    "device": "openaps://indy-e1/cgm", 
    "rssi": 175, 
    "type": "sgv", 
    "glucose": 98
  }, 
  {
    "trend_arrow": "FLAT", 
    "system_time": "2017-04-24T17:12:57", 
    "noise": 1, 
    "direction": "Flat", 
    "sgv": 90, 
    "display_time": "2017-04-24T10:29:40", 
    "date": 1493054980000.0, 
    "dateString": "2017-04-24T10:29:40", 
    "unfiltered": 103056, 
    "filtered": 104096, 
    "device": "openaps://indy-e1/cgm", 
    "rssi": 183, 
    "type": "sgv", 
    "glucose": 90
  }, 
  {
    "trend_arrow": "FLAT", 
    "system_time": "2017-04-24T17:07:57", 
    "noise": 1, 
    "direction": "Flat", 
    "sgv": 90, 
    "display_time": "2017-04-24T10:24:40", 
    "date": 1493054680000.0, 
    "dateString": "2017-04-24T10:24:40", 
    "unfiltered": 103328, 
    "filtered": 104976, 
    "device": "openaps://indy-e1/cgm", 
    "rssi": 174, 
    "type": "sgv", 
    "glucose": 90
  }, 
  {
    "trend_arrow": "FLAT", 
    "system_time": "2017-04-24T17:02:57", 
    "noise": 1, 
    "direction": "Flat", 
    "sgv": 91, 
    "display_time": "2017-04-24T10:19:40", 
    "date": 1493054380000.0, 
    "dateString": "2017-04-24T10:19:40", 
    "unfiltered": 103872, 
    "filtered": 104912, 
    "device": "openaps://indy-e1/cgm", 
    "rssi": 185, 
    "type": "sgv", 
    "glucose": 91
  }
]