[
  {
    "trend_arrow": "45_DOWN", 
    "display_time": "2017-04-02T16:50:41-07:00", 
    "noise": 1, 
    "system_time": "2017-04-02T23:49:41-07:00", 
    "direction": "FortyFiveDown", 
    "sgv": 142, 
    "dateString": "2017-04-02T16:50:41-07:00", 
    "device": "openaps://indy-e1/cgm", 
    "unfiltered": 148608, 
    "rssi": 195, 
    "date": 1491177041000, 
    "filtered": 156448, 
    "type": "sgv", 
    "glucose": 142
  }, 
  {
    "trend_arrow": "45_DOWN", 
    "display_time": "2017-04-02T16:45:41-07:00", 
    "noise": 1, 
    "system_time": "2017-04-02T23:44:41-07:00", 
    "direction": "FortyFiveDown", 
    "sgv": 148, 
    "dateString": "2017-04-02T16:45:41-07:00", 
    "device": "openaps://indy-e1/cgm", 
    "unfiltered": 153728, 
    "rssi": 198, 
    "date": 1491176741000, 
    "filtered": 161632, 
    "type": "sgv", 
    "glucose": 148
  }
]