[
  {
    "trend_arrow": "FLAT", 
    "display_time": "2017-04-18T12:09:23-07:00", 
    "noise": 1, 
    "system_time": "2017-04-18T19:08:19-07:00", 
    "direction": "Flat", 
    "sgv": 136, 
    "dateString": "2017-04-18T12:09:23-07:00", 
    "device": "openaps://indy-e1/cgm", 
    "unfiltered": 140608, 
    "rssi": 193, 
    "date": 1492542563000, 
    "filtered": 145056, 
    "type": "sgv", 
    "glucose": 136
  }, 
  {
    "trend_arrow": "FLAT", 
    "display_time": "2017-04-18T12:04:23-07:00", 
    "noise": 1, 
    "system_time": "2017-04-18T19:03:19-07:00", 
    "direction": "Flat", 
    "sgv": 140, 
    "dateString": "2017-04-18T12:04:23-07:00", 
    "device": "openaps://indy-e1/cgm", 
    "unfiltered": 143680, 
    "rssi": 198, 
    "date": 1492542263000, 
    "filtered": 147456, 
    "type": "sgv", 
    "glucose": 140
  }
]