[
  {
    "trend_arrow": "FLAT", 
    "display_time": "2017-04-06T15:30:29-07:00", 
    "noise": 1, 
    "system_time": "2017-04-06T22:29:29-07:00", 
    "direction": "Flat", 
    "sgv": 72, 
    "dateString": "2017-04-06T15:30:29-07:00", 
    "device": "openaps://indy-e1/cgm", 
    "unfiltered": 92880, 
    "rssi": 187, 
    "date": 1491517829000, 
    "filtered": 100928, 
    "type": "sgv", 
    "glucose": 72
  }, 
  {
    "trend_arrow": "FLAT", 
    "display_time": "2017-04-06T15:25:29-07:00", 
    "noise": 1, 
    "system_time": "2017-04-06T22:24:29-07:00", 
    "direction": "Flat", 
    "sgv": 78, 
    "dateString": "2017-04-06T15:25:29-07:00", 
    "device": "openaps://indy-e1/cgm", 
    "unfiltered": 98288, 
    "rssi": 203, 
    "date": 1491517529000, 
    "filtered": 105744, 
    "type": "sgv", 
    "glucose": 78
  }
]