[
  {
    "trend_arrow": "FLAT", 
    "display_time": "2017-04-23T01:14:13-07:00", 
    "noise": 1, 
    "system_time": "2017-04-23T08:13:08-07:00", 
    "direction": "Flat", 
    "sgv": 60, 
    "dateString": "2017-04-23T01:14:13-07:00", 
    "device": "openaps://indy-e1/cgm", 
    "unfiltered": 79200, 
    "rssi": 443, 
    "date": 1492935253000, 
    "filtered": 72384, 
    "type": "sgv", 
    "glucose": 60
  }, 
  {
    "trend_arrow": "FLAT", 
    "display_time": "2017-04-23T01:09:11-07:00", 
    "noise": 1, 
    "system_time": "2017-04-23T08:08:07-07:00", 
    "direction": "Flat", 
    "sgv": 57, 
    "dateString": "2017-04-23T01:09:11-07:00", 
    "device": "openaps://indy-e1/cgm", 
    "unfiltered": 76880, 
    "rssi": 186, 
    "date": 1492934951000, 
    "filtered": 68944, 
    "type": "sgv", 
    "glucose": 57
  }
]