[
  {
    "trend_arrow": "45_UP", 
    "display_time": "2017-04-10T18:00:17-07:00", 
    "noise": 1, 
    "system_time": "2017-04-11T00:59:17-07:00", 
    "direction": "FortyFiveUp", 
    "sgv": 144, 
    "dateString": "2017-04-10T18:00:17-07:00", 
    "device": "openaps://indy-e1/cgm", 
    "unfiltered": 161504, 
    "rssi": 448, 
    "date": 1491872417000, 
    "filtered": 150848, 
    "type": "sgv", 
    "glucose": 144
  }, 
  {
    "trend_arrow": "45_UP", 
    "display_time": "2017-04-10T17:55:17-07:00", 
    "noise": 1, 
    "system_time": "2017-04-11T00:54:16-07:00", 
    "direction": "FortyFiveUp", 
    "sgv": 138, 
    "dateString": "2017-04-10T17:55:17-07:00", 
    "device": "openaps://indy-e1/cgm", 
    "unfiltered": 154976, 
    "rssi": 184, 
    "date": 1491872117000, 
    "filtered": 142528, 
    "type": "sgv", 
    "glucose": 138
  }
]