[
  {
    "trend_arrow": "45_DOWN", 
    "display_time": "2017-04-04T14:30:35-07:00", 
    "noise": 1, 
    "system_time": "2017-04-04T21:29:35-07:00", 
    "direction": "FortyFiveDown", 
    "sgv": 65, 
    "dateString": "2017-04-04T14:30:35-07:00", 
    "device": "openaps://indy-e1/cgm", 
    "unfiltered": 82112, 
    "rssi": 196, 
    "date": 1491341435000, 
    "filtered": 89120, 
    "type": "sgv", 
    "glucose": 65
  }, 
  {
    "trend_arrow": "45_DOWN", 
    "display_time": "2017-04-04T14:25:35-07:00", 
    "noise": 1, 
    "system_time": "2017-04-04T21:24:35-07:00", 
    "direction": "FortyFiveDown", 
    "sgv": 69, 
    "dateString": "2017-04-04T14:25:35-07:00", 
    "device": "openaps://indy-e1/cgm", 
    "unfiltered": 85056, 
    "rssi": 203, 
    "date": 1491341135000, 
    "filtered": 95728, 
    "type": "sgv", 
    "glucose": 69
  }
]