[
  {
    "trend_arrow": "FLAT", 
    "display_time": "2017-04-20T16:34:17-07:00", 
    "noise": 1, 
    "system_time": "2017-04-20T23:33:13-07:00", 
    "direction": "Flat", 
    "sgv": 47, 
    "dateString": "2017-04-20T16:34:17-07:00", 
    "device": "openaps://indy-e1/cgm", 
    "unfiltered": 66640, 
    "rssi": 189, 
    "date": 1492731257000, 
    "filtered": 71024, 
    "type": "sgv", 
    "glucose": 47
  }, 
  {
    "trend_arrow": "45_DOWN", 
    "display_time": "2017-04-20T16:29:17-07:00", 
    "noise": 1, 
    "system_time": "2017-04-20T23:28:13-07:00", 
    "direction": "FortyFiveDown", 
    "sgv": 49, 
    "dateString": "2017-04-20T16:29:17-07:00", 
    "device": "openaps://indy-e1/cgm", 
    "unfiltered": 68576, 
    "rssi": 197, 
    "date": 1492730957000, 
    "filtered": 75856, 
    "type": "sgv", 
    "glucose": 49
  }
]