[
  {
    "trend_arrow": "FLAT", 
    "display_time": "2017-04-18T20:39:22-07:00", 
    "noise": 1, 
    "system_time": "2017-04-19T03:38:18-07:00", 
    "direction": "Flat", 
    "sgv": 184, 
    "dateString": "2017-04-18T20:39:22-07:00", 
    "device": "openaps://indy-e1/cgm", 
    "unfiltered": 180352, 
    "rssi": 187, 
    "date": 1492573162000, 
    "filtered": 184128, 
    "type": "sgv", 
    "glucose": 184
  }, 
  {
    "trend_arrow": "FLAT", 
    "display_time": "2017-04-18T20:34:22-07:00", 
    "noise": 1, 
    "system_time": "2017-04-19T03:33:18-07:00", 
    "direction": "Flat", 
    "sgv": 185, 
    "dateString": "2017-04-18T20:34:22-07:00", 
    "device": "openaps://indy-e1/cgm", 
    "unfiltered": 181568, 
    "rssi": 165, 
    "date": 1492572862000, 
    "filtered": 185472, 
    "type": "sgv", 
    "glucose": 185
  }
]