[
  {
    "trend_arrow": "FLAT", 
    "display_time": "2017-04-28T04:29:24-07:00", 
    "noise": 1, 
    "system_time": "2017-04-28T11:12:41-07:00", 
    "direction": "Flat", 
    "sgv": 103, 
    "dateString": "2017-04-28T04:29:24-07:00", 
    "device": "openaps://indy-e1/cgm", 
    "unfiltered": 112800, 
    "rssi": 198, 
    "date": 1493378964000, 
    "filtered": 115648, 
    "type": "sgv", 
    "glucose": 103
  }, 
  {
    "trend_arrow": "FLAT", 
    "display_time": "2017-04-28T04:24:24-07:00", 
    "noise": 1, 
    "system_time": "2017-04-28T11:07:41-07:00", 
    "direction": "Flat", 
    "sgv": 106, 
    "dateString": "2017-04-28T04:24:24-07:00", 
    "device": "openaps://indy-e1/cgm", 
    "unfiltered": 114608, 
    "rssi": 198, 
    "date": 1493378664000, 
    "filtered": 119168, 
    "type": "sgv", 
    "glucose": 106
  }
]