[
  {
    "trend_arrow": "FLAT", 
    "system_time": "2017-04-12T11:43:13", 
    "noise": 1, 
    "direction": "Flat", 
    "sgv": 68, 
    "display_time": "2017-04-12T04:59:38", 
    "date": 1491998378000.0, 
    "dateString": "2017-04-12T04:59:38", 
    "unfiltered": 85424, 
    "filtered": 81552, 
    "device": "openaps://indy-e1/cgm", 
    "rssi": 186, 
    "type": "sgv", 
    "glucose": 68
  }, 
  {
    "trend_arrow": "FLAT", 
    "system_time": "2017-04-12T11:38:13", 
    "noise": 1, 
    "direction": "Flat", 
    "sgv": 65, 
    "display_time": "2017-04-12T04:54:39", 
    "date": 1491998079000.0, 
    "dateString": "2017-04-12T04:54:39", 
    "unfiltered": 82352, 
    "filtered": 80000, 
    "device": "openaps://indy-e1/cgm", 
    "rssi": 441, 
    "type": "sgv", 
    "glucose": 65
  }, 
  {
    "trend_arrow": "FLAT", 
    "system_time": "2017-04-12T11:33:13", 
    "noise": 1, 
    "direction": "Flat", 
    "sgv": 62, 
    "display_time": "2017-04-12T04:49:38", 
    "date": 1491997778000.0, 
    "dateString": "2017-04-12T04:49:38", 
    "unfiltered": 80576, 
    "filtered": 78880, 
    "device": "openaps://indy-e1/cgm", 
    "rssi": 185, 
    "type": "sgv", 
    "glucose": 62
  }, 
  {
    "trend_arrow": "FLAT", 
    "system_time": "2017-04-12T11:28:13", 
    "noise": 1, 
    "direction": "Flat", 
    "sgv": 61, 
    "display_time": "2017-04-12T04:44:38", 
    "date": 1491997478000.0, 
    "dateString": "2017-04-12T04:44:38", 
    "unfiltered": 79392, 
    "filtered": 78416, 
    "device": "openaps://indy-e1/cgm", 
    "rssi": 197, 
    "type": "sgv", 
    "glucose": 61
  }, 
  {
    "trend_arrow": "FLAT", 
    "system_time": "2017-04-12T11:23:13", 
    "noise": 1, 
    "direction": "Flat", 
    "sgv": 61, 
    "display_time": "2017-04-12T04:39:38", 
    "date": 1491997178000.0, 
    "dateString": "2017-04-12T04:39:38", 
    "unfiltered": 79232, 
    "filtered": 79328, 
    "device": "openaps://indy-e1/cgm", 
    "rssi": 174, 
    "type": "sgv", 
    "glucose": 61
  }, 
  {
    "trend_arrow": "FLAT", 
    "system_time": "2017-04-12T11:18:13", 
    "noise": 1, 
    "direction": "Flat", 
    "sgv": 61, 
    "display_time": "2017-04-12T04:34:38", 
    "date": 1491996878000.0, 
    "dateString": "2017-04-12T04:34:38", 
    "unfiltered": 79504, 
    "filtered": 81840, 
    "device": "openaps://indy-e1/cgm", 
    "rssi": 172, 
    "type": "sgv", 
    "glucose": 61
  }
]