[
  {
    "trend_arrow": "45_UP", 
    "display_time": "2017-04-01T15:45:44-07:00", 
    "noise": 1, 
    "system_time": "2017-04-01T22:44:44-07:00", 
    "direction": "FortyFiveUp", 
    "sgv": 125, 
    "dateString": "2017-04-01T15:45:44-07:00", 
    "device": "openaps://indy-e1/cgm", 
    "unfiltered": 123136, 
    "rssi": 198, 
    "date": 1491086744000, 
    "filtered": 116176, 
    "type": "sgv", 
    "glucose": 125
  }, 
  {
    "trend_arrow": "SINGLE_UP", 
    "display_time": "2017-04-01T15:40:44-07:00", 
    "noise": 1, 
    "system_time": "2017-04-01T22:39:44-07:00", 
    "direction": "SingleUp", 
    "sgv": 121, 
    "dateString": "2017-04-01T15:40:44-07:00", 
    "device": "openaps://indy-e1/cgm", 
    "unfiltered": 120000, 
    "rssi": 195, 
    "date": 1491086444000, 
    "filtered": 107168, 
    "type": "sgv", 
    "glucose": 121
  }
]