[
  {
    "trend_arrow": "FLAT", 
    "system_time": "2017-04-02T14:34:42", 
    "noise": 1, 
    "direction": "Flat", 
    "sgv": 111, 
    "display_time": "2017-04-02T07:35:42", 
    "date": 1491143742000.0, 
    "dateString": "2017-04-02T07:35:42", 
    "unfiltered": 112768, 
    "filtered": 107888, 
    "device": "openaps://indy-e1/cgm", 
    "rssi": 197, 
    "type": "sgv", 
    "glucose": 111
  }, 
  {
    "trend_arrow": "45_UP", 
    "system_time": "2017-04-02T14:29:42", 
    "noise": 1, 
    "direction": "FortyFiveUp", 
    "sgv": 108, 
    "display_time": "2017-04-02T07:30:42", 
    "date": 1491143442000.0, 
    "dateString": "2017-04-02T07:30:42", 
    "unfiltered": 110704, 
    "filtered": 104064, 
    "device": "openaps://indy-e1/cgm", 
    "rssi": 198, 
    "type": "sgv", 
    "glucose": 108
  }, 
  {
    "trend_arrow": "FLAT", 
    "system_time": "2017-04-02T14:24:42", 
    "noise": 1, 
    "direction": "Flat", 
    "sgv": 103, 
    "display_time": "2017-04-02T07:25:42", 
    "date": 1491143142000.0, 
    "dateString": "2017-04-02T07:25:42", 
    "unfiltered": 106528, 
    "filtered": 100640, 
    "device": "openaps://indy-e1/cgm", 
    "rssi": 186, 
    "type": "sgv", 
    "glucose": 103
  }, 
  {
    "trend_arrow": "FLAT", 
    "system_time": "2017-04-02T14:19:42", 
    "noise": 1, 
    "direction": "Flat", 
    "sgv": 97, 
    "display_time": "2017-04-02T07:20:42", 
    "date": 1491142842000.0, 
    "dateString": "2017-04-02T07:20:42", 
    "unfiltered": 102208, 
    "filtered": 97744, 
    "device": "openaps://indy-e1/cgm", 
    "rssi": 187, 
    "type": "sgv", 
    "glucose": 97
  }, 
  {
    "trend_arrow": "FLAT", 
    "system_time": "2017-04-02T14:14:42", 
    "noise": 1, 
    "direction": "Flat", 
    "sgv": 93, 
    "display_time": "2017-04-02T07:15:42", 
    "date": 1491142542000.0, 
    "dateString": "2017-04-02T07:15:42", 
    "unfiltered": 98800, 
    "filtered": 95264, 
    "device": "openaps://indy-e1/cgm", 
    "rssi": 187, 
    "type": "sgv", 
    "glucose": 93
  }, 
  {
    "trend_arrow": "FLAT", 
    "system_time": "2017-04-02T14:09:42", 
    "noise": 1, 
    "direction": "Flat", 
    "sgv": 90, 
    "display_time": "2017-04-02T07:10:42", 
    "date": 1491142242000.0, 
    "dateString": "2017-04-02T07:10:42", 
    "unfiltered": 96768, 
    "filtered": 93248, 
    "device": "openaps://indy-e1/cgm", 
    "rssi": 187, 
    "type": "sgv", 
    "glucose": 90
  }
]