[
  {
    "trend_arrow": "FLAT", 
    "system_time": "2017-04-11T04:54:16", 
    "noise": 1, 
    "direction": "Flat", 
    "sgv": 159, 
    "display_time": "2017-04-10T21:55:16", 
    "date": 1491886516000.0, 
    "dateString": "2017-04-10T21:55:16", 
    "unfiltered": 176800, 
    "filtered": 175968, 
    "device": "openaps://indy-e1/cgm", 
    "rssi": 180, 
    "type": "sgv", 
    "glucose": 159
  }, 
  {
    "trend_arrow": "FLAT", 
    "system_time": "2017-04-11T04:49:16", 
    "noise": 1, 
    "direction": "Flat", 
    "sgv": 159, 
    "display_time": "2017-04-10T21:50:16", 
    "date": 1491886216000.0, 
    "dateString": "2017-04-10T21:50:16", 
    "unfiltered": 176960, 
    "filtered": 174176, 
    "device": "openaps://indy-e1/cgm", 
    "rssi": 168, 
    "type": "sgv", 
    "glucose": 159
  }, 
  {
    "trend_arrow": "FLAT", 
    "system_time": "2017-04-11T04:44:16", 
    "noise": 1, 
    "direction": "Flat", 
    "sgv": 158, 
    "display_time": "2017-04-10T21:45:16", 
    "date": 1491885916000.0, 
    "dateString": "2017-04-10T21:45:16", 
    "unfiltered": 175360, 
    "filtered": 171552, 
    "device": "openaps://indy-e1/cgm", 
    "rssi": 166, 
    "type": "sgv", 
    "glucose": 158
  }, 
  {
    "trend_arrow": "FLAT", 
    "system_time": "2017-04-11T04:39:16", 
    "noise": 1, 
    "direction": "Flat", 
    "sgv": 155, 
    "display_time": "2017-04-10T21:40:16", 
    "date": 1491885616000.0, 
    "dateString": "2017-04-10T21:40:16", 
    "unfiltered": 172416, 
    "filtered": 168064, 
    "device": "openaps://indy-e1/cgm", 
    "rssi": 173, 
    "type": "sgv", 
    "glucose": 155
  }, 
  {
    "trend_arrow": "FLAT", 
    "system_time": "2017-04-11T04:34:16", 
    "noise": 1, 
    "direction": "Flat", 
    "sgv": 153, 
    "display_time": "2017-04-10T21:35:16", 
    "date": 1491885316000.0, 
    "dateString": "2017-04-10T21:35:16", 
    "unfiltered": 170752, 
    "filtered": 163808, 
    "device": "openaps://indy-e1/cgm", 
    "rssi": 174, 
    "type": "sgv", 
    "glucose": 153
  }, 
  {
    "trend_arrow": "FLAT", 
    "system_time": "2017-04-11T04:29:16", 
    "noise": 1, 
    "direction": "Flat", 
    "sgv": 149, 
    "display_time": "2017-04-10T21:30:16", 
    "date": 1491885016000.0, 
    "dateString": "2017-04-10T21:30:16", 
    "unfiltered": 165760, 
    "filtered": 159136, 
    "device": "openaps://indy-e1/cgm", 
    "rssi": 166, 
    "type": "sgv", 
    "glucose": 149
  }
]