[
  {
    "trend_arrow": "FLAT", 
    "display_time": "2017-04-08T21:15:23-07:00", 
    "noise": 1, 
    "system_time": "2017-04-09T04:14:22-07:00", 
    "direction": "Flat", 
    "sgv": 81, 
    "dateString": "2017-04-08T21:15:23-07:00", 
    "device": "openaps://indy-e1/cgm", 
    "unfiltered": 101808, 
    "rssi": 443, 
    "date": 1491711323000, 
    "filtered": 103200, 
    "type": "sgv", 
    "glucose": 81
  }, 
  {
    "trend_arrow": "45_DOWN", 
    "display_time": "2017-04-08T21:10:22-07:00", 
    "noise": 1, 
    "system_time": "2017-04-09T04:09:22-07:00", 
    "direction": "FortyFiveDown", 
    "sgv": 83, 
    "dateString": "2017-04-08T21:10:22-07:00", 
    "device": "openaps://indy-e1/cgm", 
    "unfiltered": 103664, 
    "rssi": 186, 
    "date": 1491711022000, 
    "filtered": 109376, 
    "type": "sgv", 
    "glucose": 83
  }
]