[
  {
    "trend_arrow": "FLAT", 
    "display_time": "2017-03-25T16:35:22-07:00", 
    "noise": 1, 
    "system_time": "2017-03-25T23:19:23-07:00", 
    "direction": "Flat", 
    "sgv": 97, 
    "dateString": "2017-03-25T16:35:22-07:00", 
    "device": "openaps://indy-e1/cgm", 
    "unfiltered": 105616, 
    "rssi": 195, 
    "date": 1490484922000, 
    "filtered": 107136, 
    "type": "sgv", 
    "glucose": 97
  }, 
  {
    "trend_arrow": "NOT_COMPUTABLE", 
    "display_time": "2017-03-25T16:30:23-07:00", 
    "noise": 1, 
    "system_time": "2017-03-25T23:14:25-07:00", 
    "direction": "NOT COMPUTABLE", 
    "sgv": 102, 
    "dateString": "2017-03-25T16:30:23-07:00", 
    "device": "openaps://indy-e1/cgm", 
    "unfiltered": 108944, 
    "rssi": 936, 
    "date": 1490484623000, 
    "filtered": 104912, 
    "type": "sgv", 
    "glucose": 102
  }
]