[
  {
    "trend_arrow": "FLAT", 
    "display_time": "2017-04-01T06:20:45-07:00", 
    "noise": 1, 
    "system_time": "2017-04-01T13:19:45-07:00", 
    "direction": "Flat", 
    "sgv": 100, 
    "dateString": "2017-04-01T06:20:45-07:00", 
    "device": "openaps://indy-e1/cgm", 
    "unfiltered": 108688, 
    "rssi": 193, 
    "date": 1491052845000, 
    "filtered": 113520, 
    "type": "sgv", 
    "glucose": 100
  }, 
  {
    "trend_arrow": "FLAT", 
    "display_time": "2017-04-01T06:15:45-07:00", 
    "noise": 1, 
    "system_time": "2017-04-01T13:14:45-07:00", 
    "direction": "Flat", 
    "sgv": 103, 
    "dateString": "2017-04-01T06:15:45-07:00", 
    "device": "openaps://indy-e1/cgm", 
    "unfiltered": 111584, 
    "rssi": 193, 
    "date": 1491052545000, 
    "filtered": 116016, 
    "type": "sgv", 
    "glucose": 103
  }
]