[
  {
    "trend_arrow": "FLAT", 
    "display_time": "2017-04-19T17:44:20-07:00", 
    "noise": 1, 
    "system_time": "2017-04-20T00:43:15-07:00", 
    "direction": "Flat", 
    "sgv": 105, 
    "dateString": "2017-04-19T17:44:20-07:00", 
    "device": "openaps://indy-e1/cgm", 
    "unfiltered": 115520, 
    "rssi": 207, 
    "date": 1492649060000, 
    "filtered": 116304, 
    "type": "sgv", 
    "glucose": 105
  }, 
  {
    "trend_arrow": "FLAT", 
    "display_time": "2017-04-19T17:39:20-07:00", 
    "noise": 1, 
    "system_time": "2017-04-20T00:38:15-07:00", 
    "direction": "Flat", 
    "sgv": 105, 
    "dateString": "2017-04-19T17:39:20-07:00", 
    "device": "openaps://indy-e1/cgm", 
    "unfiltered": 115472, 
    "rssi": 196, 
    "date": 1492648760000, 
    "filtered": 119296, 
    "type": "sgv", 
    "glucose": 105
  }
]